deepview_data/__init__.py
deepview_data/_custom_datasets.py
deepview_data/py.typed
deepview_data-3.9.6.dist-info/WHEEL
deepview_data-3.9.6.dist-info/METADATA
deepview_data-3.9.6.dist-info/RECORD
